acolite/__init__.py
acolite/acolite.py
acolite/cli.py
acolite/common.py
acolite-0.0.1.dist-info/LICENSE
acolite-0.0.1.dist-info/METADATA
acolite-0.0.1.dist-info/WHEEL
acolite-0.0.1.dist-info/entry_points.txt
acolite-0.0.1.dist-info/top_level.txt
acolite-0.0.1.dist-info/RECORD
